keycloak_django_utils/__init__.py
keycloak_django_utils/authentication.py
keycloak_django_utils/jwt.py
keycloak_django_utils/permissions.py
keycloak_django_utils-0.3.0.dist-info/LICENSE
keycloak_django_utils-0.3.0.dist-info/METADATA
keycloak_django_utils-0.3.0.dist-info/WHEEL
keycloak_django_utils-0.3.0.dist-info/top_level.txt
keycloak_django_utils-0.3.0.dist-info/RECORD
