Metadata-Version: 2.1
Name: keycloak-django-utils
Version: 0.3.0
Summary: Python Boilerplate contains all the boilerplate you need to create a Python package.
Home-page: https://github.com/lucas8107/keycloak_django_utils
Author: Lucas Paula
Author-email: luolcami@gmail.com
License: MIT license
Keywords: keycloak_django_utils
Platform: UNKNOWN
Classifier: Development Status :: 2 - Pre-Alpha
Classifier: Intended Audience :: Developers
Classifier: License :: OSI Approved :: MIT License
Classifier: Natural Language :: English
Classifier: Programming Language :: Python :: 3
Classifier: Programming Language :: Python :: 3.6
Classifier: Programming Language :: Python :: 3.7
Classifier: Programming Language :: Python :: 3.8
Requires-Python: >=3.6
Requires-Dist: Django
Requires-Dist: djangorestframework
Requires-Dist: pyjwt
Requires-Dist: requests
